hdcutils/__init__.py
hdcutils/_adb_mapping.py
hdcutils/_device.py
hdcutils/_hdc.py
hdcutils/extension/__init__.py
hdcutils/extension/_ability_assistant.py
hdcutils/extension/_base.py
hdcutils/extension/_bundle_manager.py
hdcutils/extension/_hidumper.py
hdcutils/extension/_hilog.py
hdcutils/extension/_param.py
hdcutils/extension/_power_shell.py
hdcutils/extension/_uitest.py
hdcutils-0.1.4.dist-info/licenses/LICENSE
hdcutils-0.1.4.dist-info/METADATA
hdcutils-0.1.4.dist-info/WHEEL
hdcutils-0.1.4.dist-info/top_level.txt
hdcutils-0.1.4.dist-info/RECORD
