Metadata-Version: 2.4
Name: hdcutils
Version: 0.1.4
Summary: Pure python hdc library for harmony hdc service.
Author-email: lanbaoshen <lanbaoshen@icloud.com>
Requires-Python: >=3.10
License-File: LICENSE
Requires-Dist: loguru>=0.7.3
Dynamic: license-file
